Workbook

Sheet CXC(CARTERA)
A1: FEHCA FE | B1: # FE | C1: CLIENTE | D1: CONCEPTO | E1: VALOR BRUTO FACTURADO | F1: IVA | G1: RETENCIONES PRACTICADAS | H1: NETO FACTURADO DEL PERIODO | I1: SALDO ANTERIOR | J1: PAGOS Y ABONOS RECIBIDOS | K1: TOTAL DE CUENTAS POR COBRAR AL PERIODO
A3: 45678 | B3: FE-239 | C3: PERANITO | D3: SILLAS | E3: 2000000 | F3: 0 | H3: =E3+F3-G3 -> 2000000 | I3: 0 | J3: 2000000 | K3: =H3+I3-J3 -> 0
A4: 45678 | B4: FE-240 | C4: TAL FULANO | D4: ESCRITORIO | E4: 2000000 | F4: =E4*19% -> 380000 | G4: =F4*15% -> 57000 | H4: =E4+F4-G4 -> 2323000 | I4: 5561000 | K4: =H4+I4-J4 -> 7884000
A5: 45678 | B5: FE-241 | C5: PERANO | D5: ESCRITORIO | E5: 2000000 | F5: =E5*19% -> 380000 | G5: =F5*15% -> 57000 | H5: =E5+F5-G5 -> 2323000 | I5: 5561000 | K5: =H5+I5-J5 -> 7884000
A6: 45678 | B6: FE-242 | C6: SULTANEJO | D6: ESCRITORIO | E6: 2000000 | F6: =E6*19% -> 380000 | G6: =F6*15% -> 57000 | H6: =E6+F6-G6 -> 2323000 | I6: 5561000 | K6: =H6+I6-J6 -> 7884000
A7: 45678 | B7: FE-243 | C7: TAL FULANO | D7: ESCRITORIO | E7: 2000000 | F7: =E7*19% -> 380000 | G7: =F7*15% -> 57000 | H7: =E7+F7-G7 -> 2323000 | I7: 5561000 | K7: =H7+I7-J7 -> 7884000
K8: =H8+I8-J8 -> 0
K9: =H9+I9-J9 -> 0
A10: TOTALES DEL PERIODO | E10: =SUM(E3:E9) -> 10000000 | F10: =SUM(F3:F9) -> 1520000 | G10: =SUM(G3:G9) -> 228000 | H10: =SUM(H3:H9) -> 11292000 | I10: =SUM(I3:I9) -> 22244000 | J10: =SUM(J3:J9) -> 2000000 | K10: =SUM(K3:K9) -> 31536000
A12: 45707 | B12: FE-247 | C12: CLINICA MEDICO-ODONTOLOGICA PROMTA S.A.S | D12: DES PAG WEB | E12: 2000000 | F12: 0 | H12: =E12+F12-G12 -> 2000000 | I12: =K3 -> 0 | J12: 2000000 | K12: =H12+I12-J12 -> 0
A13: 45707 | B13: FE-248 | C13: CDI EXHIBICIONES S.A.S | D13: CONSULTORIA DE MERCADEO | E13: 2000000 | F13: =E13*19% -> 380000 | G13: 0 | H13: =E13+F13-G13 -> 2380000 | I13: =K4 -> 7884000 | J13: =2323000+2323000 -> 4646000 | K13: =H13+I13-J13 -> 5618000
A14: 45707 | B14: FE-249 | C14: PERANO | D14: CONSULTORIA DE MERCADEO | E14: 2000000 | F14: =E14*19% -> 380000 | G14: =F14*15% -> 57000 | H14: =E14+F14-G14 -> 2323000 | I14: =K5 -> 7884000 | J14: 0 | K14: =H14+I14-J14 -> 10207000
A15: 45707 | B15: FE-250 | C15: SULTANEJO | D15: CONSULTORIA DE MERCADEO | E15: 2000000 | F15: =E15*19% -> 380000 | G15: =F15*15% -> 57000 | H15: =E15+F15-G15 -> 2323000 | I15: =K6 -> 7884000 | J15: =2323000+2323000 -> 4646000 | K15: =H15+I15-J15 -> 5561000
A16: 45707 | B16: FE-251 | C16: TAL FULANO | D16: CONSULTORIA DE MERCADEO | E16: 2000000 | F16: =E16*19% -> 380000 | G16: =F16*15% -> 57000 | H16: =E16+F16-G16 -> 2323000 | I16: =K7 -> 7884000 | J16: =2323000+2323000 -> 4646000 | K16: =H16+I16-J16 -> 5561000
K18: =H18+I18-J18 -> 0
A19: TOTALES DEL PERIODO | E19: =SUM(E12:E18) -> 10000000 | F19: =SUM(F12:F18) -> 1520000 | G19: =SUM(G12:G18) -> 171000 | H19: =SUM(H12:H18) -> 11349000 | I19: =SUM(I12:I18) -> 31536000 | J19: =SUM(J12:J18) -> 15938000 | K19: =SUM(K12:K18) -> 26947000

Sheet CXP (EGRESOS)
A1: FECHA | B1: # FE / CUENTAS DE COBRO | C1: PROOVEEDOR | D1: CONCEPTO | E1: VALOR BRUTO | F1: IMPUESTO | G1: VALOR NETO | H1: SALDO DEL PERIODO ANTERIOR | I1: ABONO DEL PERIODO | J1: SALDOS PENDIENTES POR PAGAR A LA FECHA | L1: ESTADO (GENERA EL PDF)
C3: ALEJANDRO ROMERO | D3: NOMINA Q1 Y Q2 | E3: 1510000 | G3: =E3+F3 -> 1510000 | H3: 679000 | I3: =679000+679000+76000+755000 -> 2189000 | J3: =+G3+H3-I3 -> 0 | K3: =+J3 -> 0 | L3: EN LA "J2 Y J3" QUE SON LOS SALDOS DE NÓMINA, DEBE LLEVAR UNA COFNIGURACION ESPECIAL, ES DECIR, QUE SOLO ME TOME EL 50% DE LA NOMINA, ES DECIR, LO SEPARE POR QUINCENAS, DEL 1 AL 15 SERÍA LA Q1 Y DEL 16 AL 30 O 31, SERÍA LA Q2, SI SE LLEGARA A HAVER IN ABONO O DESCUENRTRO, SÓLO SE LE RESTE A ESE QUINCENA EN ESPECIAL.
C4: SOFIA LOPERA (HIJA CRISTINA) | D4: NOMINA Q1 Y Q2 | E4: 1423500 | G4: =E4+F4 -> 1423500 | I4: 522000 | J4: =+G4+H4-I4 -> 901500 | K4: 0
C5: SEGURIDAD SOCIAL | D5: SEGURIDAD SOCIAL | E5: 318800 | G5: =E5+F5 -> 318800 | H5: 0 | I5: 318800 | J5: =+G5+H5-I5 -> 0 | K5: =+J5 -> 0
C6: PRESTACIONES SOC. EMPLEADOS | D6: INTERES CESANTÍAS ALEJANDRO | E6: 175400 | G6: =E6+F6 -> 175400 | H6: 0 | I6: 175400 | J6: =+G6+H6-I6 -> 0 | K6: =+J6 -> 0
C7: Maria Camila (+ cta de cobro Nury ) | D7: COMIONES SERVICIOS CONSULT. Y MARKETING + REEMBOLSOM TRANSP | E7: 3065500 | G7: =E7+F7 -> 3065500 | H7: 3235500 | I7: =235000+3000000+61000 -> 3296000 | J7: =+G7+H7-I7 -> 3005000 | K7: =+J7/2 -> 1502500
C8: Jhon Penagos - CLARA INES | D8: COMIONES SERVICIOS CONSULT. Y MARKETING | G8: =E8+F8 -> 0 | H8: 0 | J8: =+G8+H8-I8 -> 0 | K8: =+J8 -> 0
C9: Reinaldo Jaramillo | D9: HONORARIOS CONTABLES | E9: 950000 | G9: =E9+F9 -> 950000 | H9: 0 | J9: =+G9+H9-I9 -> 950000 | K9: =+J9 -> 950000
C10: PERANO | D10: HONORARIOS ADMON | E10: 5000000 | G10: =E10+F10 -> 5000000 | H10: 0 | J10: =+G10+H10-I10 -> 5000000
E11: =SUM(E3:E9) -> 7443200 | F11: =SUM(F3:F9) -> 0 | G11: =SUM(G3:G9) -> 7443200 | H11: =SUM(H3:H9) -> 3914500 | I11: =SUM(I3:I9) -> 6501200 | J11: =SUM(J3:J9) -> 4856500 | K11: =+J11 -> 4856500
C14: ALEJANDRO ROMERO | D14: NOMINA Q1 Y Q2 | E14: 1510000 | G14: =E14+F14 -> 1510000 | H14: 0 | I14: 755000 | J14: =+G14+H14-I14 -> 755000
C15: SOFIA LOPERA (HIJA CRISTINA) | D15: NOMINA Q1 Y Q2 | E15: 1424000 | G15: =E15+F15 -> 1424000 | H15: =+J4 -> 901500 | I15: 712000 | J15: =+G15+H15-I15 -> 1613500
C16: SEGURIDAD SOCIAL | D16: SEGURIDAD SOCIAL | E16: 356800 | G16: =E16+F16 -> 356800 | H16: 0 | I16: 356800 | J16: =+G16+H16-I16 -> 0
C17: PRESTACIONES SOC. EMPLEADOS | D17: INTERES CESANTÍAS ALEJANDRO | G17: =E17+F17 -> 0 | H17: 100000 | J17: =+G17+H17-I17 -> 100000
C18: Maria Camila (+ cta de cobro Nury ) | D18: COMIONES SERVICIOS CONSULT. Y MARKETING + REEMBOLSOM TRANSP | E18: 3322000 | G18: =E18+F18 -> 3322000 | H18: =J7 -> 3005000 | I18: =2000000+1005000 -> 3005000 | J18: =+G18+H18-I18 -> 3322000
C19: Jhon Penagos - CLARA INES | D19: COMIONES SERVICIOS CONSULT. Y MARKETING | G19: =E19+F19 -> 0 | H19: =J8 -> 0 | J19: =+G19+H19-I19 -> 0
C20: Reinaldo Jaramillo | D20: HONORARIOS CONTABLES | E20: 950000 | G20: =E20+F20 -> 950000 | H20: =J9 -> 950000 | J20: =+G20+H20-I20 -> 1900000
C21: PERANO | D21: HONORARIOS ADMON | E21: 5000000 | G21: =E21+F21 -> 5000000 | H21: =J10 -> 5000000 | I21: 5000000 | J21: =+G21+H21-I21 -> 5000000
E22: =SUM(E14:E20) -> 7562800 | F22: =SUM(F14:F20) -> 0 | G22: =SUM(G14:G20) -> 7562800 | H22: =SUM(H14:H20) -> 4956500 | I22: =SUM(I14:I20) -> 4828800 | J22: =SUM(J14:J20) -> 7690500

Sheet EST.RES
B2: ESTADO DE RESULTADO MENSUAL
E3: ENERO | F3: FEBRERO | H3: SIEMRPE MUESTRE LOS DOS ULTIMOS MESES
B4: INGRESOS DEL MES | E4: =SUM(E5:E6)-E7 -> 10000000 | F4: =SUM(F5:F6)-F7 -> 10000000
B5: CONSULTORIAS DE MERCADEO | E5: ='CXC(CARTERA)'!E10 -> 10000000 | F5: ='CXC(CARTERA)'!E19-F6 -> 7595000
B6: DES PAG WEB, PIEZAS Y OTROS | F6: ='CXC(CARTERA)'!E14+405000 -> 2405000
B7: DEVOCLCIÓN EN VENTAS
B9: COSTOS MERCADEO | E9: =SUM(E10:E11) -> 5999000 | F9: =SUM(F10:F11) -> 6256000
B10: NÓMINA | E10: =+'CXP (EGRESOS)'!E3+'CXP (EGRESOS)'!E4 -> 2933500 | F10: =+'CXP (EGRESOS)'!E14+'CXP (EGRESOS)'!E15 -> 2934000
B11: SERVICIO DE MARKETING DE TERCEROS | E11: =+'CXP (EGRESOS)'!E7+'CXP (EGRESOS)'!E8 -> 3065500 | F11: =+'CXP (EGRESOS)'!E18+'CXP (EGRESOS)'!E19 -> 3322000
B13: UTILIDAD BRUTA | E13: =E4-E9 -> 4001000 | F13: =F4-F9 -> 3744000
B15: GASTOS ADMINISTRATIVOS | E15: =SUM(E16:E18) -> 6268800 | F15: =SUM(F16:F18) -> 6306800
B16: HONORARIOS ADMON | E16: =+'CXP (EGRESOS)'!E10 -> 5000000 | F16: =+'CXP (EGRESOS)'!E21 -> 5000000
B17: HONORARIOS CONTABLES | E17: =+'CXP (EGRESOS)'!E9 -> 950000 | F17: =+'CXP (EGRESOS)'!E20 -> 950000
B18: SEGURIDAD SOCIAL | E18: =+'CXP (EGRESOS)'!E5 -> 318800 | F18: =+'CXP (EGRESOS)'!E16 -> 356800
B19: CESANTIAS | E19: =+'CXP (EGRESOS)'!E6 -> 175400 | F19: =+'CXP (EGRESOS)'!E17 -> 0
B21: UTILIDAD OPERACIONAL | E21: =E13-E15 -> -2267800 | F21: =F13-F15 -> -2562800
B23: OTROS COSTOS Y GASTOS | E23: =SUM(E24:E25) -> 0 | F23: =SUM(F24:F25) -> 0
B24: INGRESOS FINANCIEROS | E24: 0 | F24: 0 | G24: ESTOS SE INGRESAN LOS VALORES , PORQUE SE CALCULAN EXTERNAMENTE
B25: GASTOS BANCARIOS 4X1000 | G25: ESTOS SE INGRESAN LOS VALORES , PORQUE SE CALCULAN EXTERNAMENTE
B27: UTILIDAD ANTES DE IMPUESTOS | E27: =E21-E23 -> -2267800 | F27: =F21-F23 -> -2562800
B30: GASTOS POR IMPUESTOS | G30: ESTOS SE INGRESAN LOS VALORES , PORQUE SE CALCULAN EXTERNAMENTE
B32: UTILIDAD/GANACIA DEL MES | E32: =E27-E30 -> -2267800 | F32: =F27-F30 -> -2562800

Sheet FLUJO DE CAJA
B2: FLUJO DE CAJA PROYECTADO
C3: ENERO(PROYECTADO) | D3: ENERO (REAL) | E3: % DE EJECUCION | F3: FEBRERO(PROYECTADO) | G3: FEBRERO (REAL) | H3: % DE EJECUCION
B5: Saldo inicial | C5: 18531975 | D5: 18531975
J6: PENDIENTE
B7: Ingresos por operaciones/facturado del periodo | C7: =#REF! -> #REF! | D7: =#REF!+#REF!+#REF!+#REF! -> #REF!
B8: Ingresos por recuperación de cartera | C8: =#REF! -> #REF! | D8: =#REF!-D7 -> #REF! | E8: =D8/C8 -> #REF!
B9: Total Ingresos | C9: =C7+C8 -> #REF! | D9: =D7+D8 -> #REF! | E9: =D9/C9 -> #REF!
B11: Egresos
B12: Pago de nómina | C12: ='CXP (EGRESOS)'!#REF!+'CXP (EGRESOS)'!#REF!+'CXP (EGRESOS)'!#REF!+'CXP (EGRESOS)'!#REF! -> #REF! | D12: ='CXP (EGRESOS)'!#REF!+'CXP (EGRESOS)'!#REF! -> #REF! | E12: =D12/C12 -> #REF!
B13: Pago prestaciones sociales
B14: Pago de Seguridad social | C14: ='CXP (EGRESOS)'!#REF! -> #REF! | D14: ='CXP (EGRESOS)'!#REF! -> #REF! | E14: =D14/C14 -> #REF!
B15: Pago proveedores servicios | C15: ='CXP (EGRESOS)'!#REF!+'CXP (EGRESOS)'!#REF!+'CXP (EGRESOS)'!#REF!+'CXP (EGRESOS)'!#REF!+'CXP (EGRESOS)'!#REF!+'CXP (EGRESOS)'!#REF!+'CXP (EGRESOS)'!#REF!+'CXP (EGRESOS)'!#REF!+'CXP (EGRESOS)'!#REF!+'CXP (EGRESOS)'!#REF!+'CXP (EGRESOS)'!#REF!+'CXP (EGRESOS)'!#REF!+'CXP (EGRESOS)'!#REF!+'CXP (EGRESOS)'!#REF!+'CXP (EGRESOS)'!#REF!+'CXP (EGRESOS)'!#REF!+'CXP (EGRESOS)'!#REF!+'CXP (EGRESOS)'!#REF!+'CXP (EGRESOS)'!#REF!+'CXP (EGRESOS)'!#REF!+'CXP (EGRESOS)'!#REF!+'CXP (EGRESOS)'!#REF!+'CXP (EGRESOS)'!#REF!+'CXP (EGRESOS)'!#REF!+'CXP (EGRESOS)'!#REF!+'CXP (EGRESOS)'!#REF!+'CXP (EGRESOS)'!#REF!+'CXP (EGRESOS)'!#REF!+'CXP (EGRESOS)'!#REF!+'CXP (EGRESOS)'!#REF!+'CXP (EGRESOS)'!#REF!+'CXP (EGRESOS)'!#REF!+'CXP (EGRESOS)'!#REF!+'CXP (EGRESOS)'!#REF! -> #REF! | D15: ='CXP (EGRESOS)'!#REF!+'CXP (EGRESOS)'!#REF!+'CXP (EGRESOS)'!#REF!+'CXP (EGRESOS)'!#REF!+'CXP (EGRESOS)'!#REF!+'CXP (EGRESOS)'!#REF!+'CXP (EGRESOS)'!#REF!+'CXP (EGRESOS)'!#REF!+'CXP (EGRESOS)'!#REF!+'CXP (EGRESOS)'!#REF!+'CXP (EGRESOS)'!#REF!+'CXP (EGRESOS)'!#REF!+'CXP (EGRESOS)'!#REF!+'CXP (EGRESOS)'!#REF!+'CXP (EGRESOS)'!#REF!+'CXP (EGRESOS)'!#REF!+'CXP (EGRESOS)'!#REF! -> #REF! | E15: =D15/C15 -> #REF!
B16: Pago de impuestos
B17: Otros | D17: =2500000+5354000 -> 7854000
B18: Total Egresos | C18: =SUM(C12:C17) -> #REF! | D18: =SUM(D12:D17) -> #REF! | E18: =D18/C18 -> #REF!
B20: Flujo de disponible del periodo proyect./real | C20: =+C5+C9-C18 -> #REF! | D20: =+D5+D9-D18 -> #REF! | E20: =D20/C20 -> #REF!

Sheet PLANTILLAS
B2: PLANTILLA FACTURACCIÓN
B4: 1 | C4: CREAR EL CLIENTE | D4: IDENTIFICACION | E4: NOMBRES Y APELLIDOS | F4: TELEFONO | G4: DIRECCION | H4: CIUDAD | I4: CORREO
B5: 1.1 | C5: CREAR CONSUMIDOR FINAL (SE CREA CON LOS DATOS DEL PROPIETARIO Y CON NIT 222222222)
B7: FECHA | C7: #FE O RECIBO | D7: CLEINTE | E7: PRODUCTO O SERVICIO | F7: VALOR UNITARIO | G7: CANTIDAD | H7: VALOR BEUTO | I7: IMPTOS | J7: VALOR TOTAL | K7: CONTADO O CRÉDITO
B11: PLANTILLA COMPRAS DE SERVICIOS O PRODUCTOS
B13: 1 | C13: CREAR EL CLIENTE | D13: IDENTIFICACION | E13: NOMBRES Y APELLIDOS | F13: TELEFONO | G13: DIRECCION | H13: CIUDAD | I13: CORREO
B14: 1.1 | C14: CREAR CONSUMIDOR FINAL (SE CREA CON LOS DATOS DEL PROPIETARIO Y CON NIT 222222222)
B16: FECHA | C16: #FE O RECIBO | D16: PROVEEDOR | E16: PRODUCTO O SERVICIO | F16: VALOR UNITARIO | G16: CANTIDAD | H16: VALOR BEUTO | I16: IMPTOS | J16: VALOR TOTAL | K16: CONTADO O CRÉDITO
B20: PLANTILLA PAGOS O ABONOS REALIZADOS
C22: CC
C23: PROVEEDOR | D23: NOMBRES
C25: CON ESTOS DATOS, EL SISTEMA DEBE CARGAR LA INFORMACIÓN DE LAS FACTURAS PENDIENTES POR PAGAR AL PROVEEDOR
B34: PLANTILLA DE PAGOS O ABONOS RECIBIDOS
C36: CC
C37: CLIENTE | D37: NOMBRES
C39: CON ESTOS DATOS, EL SISTEMA DEBE CARGAR LA INFORMACIÓN DE LAS FACTURAS PENDIENTES POR COBRAR AL ´CLIENTE

Sheet Hoja4

Sheet ee
